{
  "slug": "panorama",
  "name": "panorama",
  "category": "AI Agent",
  "score": 40,
  "tier": "FADING",
  "evidence_tier": "public-audit-only",
  "engine": "public-surface",
  "summary": {
    "strategic_alpha": {
      "predicted": 65,
      "reasoning": "Passive intelligence angle is genuinely differentiated — most automation tools require manual mapping first."
    },
    "execution_grit": {
      "predicted": 45,
      "reasoning": "Actual URL is PH placeholder; real product URL unconfirmed, raising concerns about delivery."
    },
    "craft_and_soul": {
      "predicted": 60,
      "reasoning": "362 PH upvotes suggest reasonable UX; team-view differentiator adds craftsmanship."
    },
    "value_signal": {
      "predicted": 50,
      "reasoning": "Free tier confirmed but paid pricing unknown — partial transparency."
    }
  },
  "review_url": "https://hlido.eu/reviews/panorama/",
  "review_url_pages": "https://hlido.pages.dev/reviews/panorama/",
  "reviewed_at": "2026-05-01",
  "run_id": "run-panorama-monedagf",
  "claims": [
    {
      "id": "C01",
      "claim": "Confirm actual product URL (not PH placeholder)",
      "required": true,
      "verdict": "blocked",
      "evidence": "This website uses a security service to protect against malicious bots.",
      "source_surface": "homepage"
    },
    {
      "id": "C02",
      "claim": "Login/signup flow documented with free tier accessible",
      "required": true,
      "verdict": "blocked",
      "evidence": "No evidence returned",
      "source_surface": "homepage"
    },
    {
      "id": "C03",
      "claim": "Passive observation feature explained publicly without login",
      "required": false,
      "verdict": "blocked",
      "evidence": "No evidence returned",
      "source_surface": "homepage"
    },
    {
      "id": "C04",
      "claim": "Team collaboration view shown in screenshots or demo",
      "required": false,
      "verdict": "blocked",
      "evidence": "No evidence returned",
      "source_surface": "homepage"
    },
    {
      "id": "C05",
      "claim": "Google Workspace + Slack integrations documented",
      "required": false,
      "verdict": "blocked",
      "evidence": "No evidence returned",
      "source_surface": "homepage"
    },
    {
      "id": "C06",
      "claim": "Pricing page accessible",
      "required": false,
      "verdict": "blocked",
      "evidence": "This website uses a security service to protect against malicious bots.",
      "source_surface": "homepage"
    },
    {
      "id": "C07",
      "claim": "One-click workflow activation feature visible in public materials",
      "required": false,
      "verdict": "blocked",
      "evidence": "No evidence returned",
      "source_surface": "homepage"
    }
  ],
  "surfaces_visited": [
    {
      "id": "homepage",
      "url": "https://www.producthunt.com/products/panorama",
      "ok": true
    },
    {
      "id": "pricing",
      "url": null,
      "ok": false,
      "reason": "not-found"
    },
    {
      "id": "docs",
      "url": null,
      "ok": false,
      "reason": "not-found"
    },
    {
      "id": "integrations",
      "url": null,
      "ok": false,
      "reason": "not-found"
    },
    {
      "id": "templates",
      "url": null,
      "ok": false,
      "reason": "not-found"
    },
    {
      "id": "changelog",
      "url": null,
      "ok": false,
      "reason": "not-found"
    },
    {
      "id": "demo",
      "url": null,
      "ok": false,
      "reason": "not-found"
    }
  ],
  "required_items_total": 2,
  "required_items_passing": 0,
  "confidence": "low",
  "schema_version": "1.0",
  "generated_at": "2026-05-01T21:01:07.019Z"
}