{
  "slug": "snorkel-ai",
  "name": "Snorkel AI",
  "category": "Data",
  "score": 65,
  "tier": "FADING",
  "evidence_tier": "public-audit-only",
  "engine": "public-surface",
  "summary": "Public-surface review of Snorkel AI",
  "review_url": "https://hlido.eu/reviews/snorkel-ai/",
  "review_url_pages": "https://hlido.pages.dev/reviews/snorkel-ai/",
  "reviewed_at": "2026-05-01",
  "run_id": "run-snorkel-ai-moo243oi",
  "claims": [
    {
      "id": "C01",
      "claim": "Homepage publicly accessible and value proposition clearly stated",
      "required": true,
      "verdict": "pass",
      "evidence": "\"Snorkel helps frontier labs and AI teams develop specialized training data and environments that set their models and agents apart.\"",
      "source_surface": "homepage"
    },
    {
      "id": "C02",
      "claim": "Pricing page discoverable in 2 clicks from homepage",
      "required": true,
      "verdict": "unknown",
      "evidence": "No evidence returned",
      "source_surface": "homepage"
    },
    {
      "id": "C03",
      "claim": "Documentation or live demo accessible without login",
      "required": true,
      "verdict": "unknown",
      "evidence": "No evidence returned",
      "source_surface": "homepage"
    },
    {
      "id": "C04",
      "claim": "Integration list or supported frameworks documented",
      "required": true,
      "verdict": "pass",
      "evidence": "Our cloud and technology partners expand our platform’s interoperability within the modern ML stack, offering our Fortune 500 and government customers with seamless and security connections.",
      "source_surface": "integrations"
    },
    {
      "id": "C05",
      "claim": "Authentication / data handling claims publicly stated",
      "required": false,
      "verdict": "partial_pass",
      "evidence": "Snorkel's proprietary process is built around the decisions that determine whether training data actually drives model improvement: Calibrated expert review, Rubrics and programmatic checks, Well-specified expert-level tasks, Adjudication and provenance.",
      "source_surface": "homepage"
    }
  ],
  "surfaces_visited": [
    {
      "id": "homepage",
      "url": "https://snorkel.ai/",
      "ok": true
    },
    {
      "id": "pricing",
      "url": null,
      "ok": false,
      "reason": "not-found"
    },
    {
      "id": "docs",
      "url": null,
      "ok": false,
      "reason": "not-found"
    },
    {
      "id": "integrations",
      "url": "https://snorkel.ai/partners/",
      "ok": true
    },
    {
      "id": "templates",
      "url": null,
      "ok": false,
      "reason": "not-found"
    },
    {
      "id": "changelog",
      "url": "https://snorkel.ai/blog/",
      "ok": true
    },
    {
      "id": "demo",
      "url": null,
      "ok": false,
      "reason": "not-found"
    }
  ],
  "required_items_total": 4,
  "required_items_passing": 2,
  "confidence": "low",
  "schema_version": "1.0",
  "generated_at": "2026-05-02T08:05:56.088Z"
}