{
  "slug": "vellum-ai",
  "name": "Vellum",
  "category": "Agent Framework",
  "score": 78,
  "tier": "STEADY",
  "evidence_tier": "public-audit-only",
  "engine": "public-surface",
  "summary": "Public-surface review of Vellum",
  "review_url": "https://hlido.eu/reviews/vellum-ai/",
  "review_url_pages": "https://hlido.pages.dev/reviews/vellum-ai/",
  "reviewed_at": "2026-05-01",
  "run_id": "run-vellum-ai-monh06j2",
  "claims": [
    {
      "id": "C01",
      "claim": "Homepage publicly accessible and value proposition clearly stated",
      "required": true,
      "verdict": "pass",
      "evidence": "Your own, personal intelligence",
      "source_surface": "homepage"
    },
    {
      "id": "C02",
      "claim": "Pricing page discoverable in 2 clicks from homepage",
      "required": true,
      "verdict": "pass",
      "evidence": "The pricing page is accessible via a link labeled 'Pricing' on the homepage.",
      "source_surface": "homepage"
    },
    {
      "id": "C03",
      "claim": "Documentation or live demo accessible without login",
      "required": true,
      "verdict": "pass",
      "evidence": "Free. No credit card. No 47-step setup wizard.",
      "source_surface": "docs"
    },
    {
      "id": "C04",
      "claim": "Integration list or supported frameworks documented",
      "required": true,
      "verdict": "partial_pass",
      "evidence": "The documentation mentions 'expanded CLI' and 'managed integrations' but does not provide a comprehensive list of integrations or supported frameworks.",
      "source_surface": "docs"
    },
    {
      "id": "C05",
      "claim": "Authentication / data handling claims publicly stated",
      "required": false,
      "verdict": "partial_pass",
      "evidence": "Your data is yours. Your workspace, memories, and config live in your private Vellum Cloud account, encrypted and isolated, or on your own machine if you self-host.",
      "source_surface": "docs"
    }
  ],
  "surfaces_visited": [
    {
      "id": "homepage",
      "url": "https://www.vellum.ai/?utm_source=direct&utm_medium=none",
      "ok": true
    },
    {
      "id": "pricing",
      "url": "https://www.vellum.ai/docs/pricing",
      "ok": true
    },
    {
      "id": "docs",
      "url": "https://www.vellum.ai/docs",
      "ok": true
    },
    {
      "id": "integrations",
      "url": "https://www.vellum.ai/docs/releases#release-2026-04-21",
      "ok": true
    },
    {
      "id": "templates",
      "url": null,
      "ok": false,
      "reason": "not-found"
    },
    {
      "id": "changelog",
      "url": "https://www.vellum.ai/blog",
      "ok": true
    },
    {
      "id": "demo",
      "url": null,
      "ok": false,
      "reason": "not-found"
    }
  ],
  "required_items_total": 4,
  "required_items_passing": 3,
  "confidence": "medium",
  "schema_version": "1.0",
  "generated_at": "2026-05-01T22:15:10.706Z"
}